scraper/PagePartBlock.py
scraper/__init__.py
scraper/funcs_over_blocks.py
scraper/get_by_tds.py
scraper/imported.py
dictionarycom_ipa_scraper-2.1.0.dist-info/METADATA
dictionarycom_ipa_scraper-2.1.0.dist-info/WHEEL
dictionarycom_ipa_scraper-2.1.0.dist-info/license.txt
dictionarycom_ipa_scraper-2.1.0.dist-info/top_level.txt
dictionarycom_ipa_scraper-2.1.0.dist-info/RECORD
