Metadata-Version: 2.1
Name: dictionarycom-ipa-scraper
Version: 2.1.0
Summary: ipa and complexity scraper of dictionary.com word page html
Home-page: UNKNOWN
License: UNKNOWN
Platform: UNKNOWN
License-File: license.txt
Requires-Dist: beautifulsoup4 (<5,>=4.10.0)
